list_based_flavorpack/__init__.py
list_based_flavorpack/admin.py
list_based_flavorpack/apps.py
list_based_flavorpack/list_based_flavorpack_settings.py
list_based_flavorpack/models.py
list_based_flavorpack/utils.py
list_based_flavorpack/api/__init__.py
list_based_flavorpack/api/routers.py
list_based_flavorpack/api/serializers.py
list_based_flavorpack/api/urls.py
list_based_flavorpack/api/views.py
list_based_flavorpack/api/viewsets.py
list_based_flavorpack/generators/__init__.py
list_based_flavorpack/generators/list_based.py
list_based_flavorpack/management/__init__.py
list_based_flavorpack/management/commands/__init__.py
list_based_flavorpack/management/commands/clone_list_based_pool.py
list_based_flavorpack/migrations/0001_initial.py
list_based_flavorpack/migrations/0002_auto_20181002_1052.py
list_based_flavorpack/migrations/0003_auto_20190123_1621.py
list_based_flavorpack/migrations/0004_auto_20190214_1800.py
list_based_flavorpack/migrations/0005_auto_20191106_1755.py
list_based_flavorpack/migrations/0006_auto_20191212_1155.py
list_based_flavorpack/migrations/0007_auto_20191219_1759.py
list_based_flavorpack/migrations/0008_auto_20200401_2145.py
list_based_flavorpack/migrations/0009_auto_20200929_2130.py
list_based_flavorpack/migrations/0010_auto_20210302_1041.py
list_based_flavorpack/migrations/0011_alter_listbasedregion_options_and_more.py
list_based_flavorpack/migrations/__init__.py
list_based_flavorpack/processing_classes/__init__.py
list_based_flavorpack/processing_classes/third_party_processing/__init__.py
list_based_flavorpack/processing_classes/third_party_processing/processing.py
list_based_flavorpack/processing_classes/third_party_processing/rules.py
list_based_flavorpack/processing_classes/third_party_processing/steps/__init__.py
list_based_flavorpack/processing_classes/third_party_processing/steps/steps.py
list_based_flavorpack/processing_classes/vanilla_processing/__init__.py
list_based_flavorpack/processing_classes/vanilla_processing/processing.py
list_based_flavorpack-4.0.1.dist-info/LICENSE
list_based_flavorpack-4.0.1.dist-info/METADATA
list_based_flavorpack-4.0.1.dist-info/WHEEL
list_based_flavorpack-4.0.1.dist-info/top_level.txt
list_based_flavorpack-4.0.1.dist-info/RECORD
