Metadata-Version: 2.1
Name: list-based-flavorpack
Version: 4.0.1
Summary: Generic List-Based Flavorpack Plugin for SerialBox
Home-page: https://gitlab.com/serial-lab/list_based_flavorpack
Author: SerialLab Corp
Author-email: slab@serial-lab.com
License: GPLv3
Keywords: seriallab,quartet,list-based,list,serialbox,level-4 quartet
Platform: UNKNOWN
Classifier: Development Status :: 5 - Production/Stable
Classifier: Environment :: Web Environment
Classifier: Framework :: Django
Classifier: Intended Audience :: Developers
Classifier: License :: OSI Approved :: GNU General Public License v3 (GPLv3)
Classifier: Natural Language :: English
Classifier: Programming Language :: Python :: 3.10
Classifier: Programming Language :: Python :: 3.11
Classifier: Programming Language :: Python :: 3.12
